{
  "machines_scheduling": [
    {
      "machine_id": 5,
      "sum_completion_time": 9276.0,
      "solve_time_seconds": 13.694,
      "jobs": [
        {
          "job_id": 147,
          "start": 478,
          "end": 491,
          "sub_machine": 0
        },
        {
          "job_id": 148,
          "start": 492,
          "end": 505,
          "sub_machine": 0
        },
        {
          "job_id": 157,
          "start": 464,
          "end": 477,
          "sub_machine": 0
        },
        {
          "job_id": 158,
          "start": 450,
          "end": 463,
          "sub_machine": 0
        },
        {
          "job_id": 167,
          "start": 780,
          "end": 793,
          "sub_machine": 0
        },
        {
          "job_id": 168,
          "start": 766,
          "end": 779,
          "sub_machine": 0
        },
        {
          "job_id": 177,
          "start": 738,
          "end": 751,
          "sub_machine": 0
        },
        {
          "job_id": 178,
          "start": 752,
          "end": 765,
          "sub_machine": 0
        },
        {
          "job_id": 187,
          "start": 1026,
          "end": 1039,
          "sub_machine": 0
        },
        {
          "job_id": 188,
          "start": 1040,
          "end": 1053,
          "sub_machine": 0
        },
        {
          "job_id": 197,
          "start": 1068,
          "end": 1081,
          "sub_machine": 0
        },
        {
          "job_id": 198,
          "start": 1054,
          "end": 1067,
          "sub_machine": 0
        }
      ]
    }
  ]
}